panvalidator/__init__.py
panvalidator/panvalidator.py
tests/__init__.py
tests/test_all_digits_pan_validator.py
tests/test_composite_pan_validator.py
tests/test_length_pan_validator.py
tests/test_luhn_pan_validator.py
tests/test_payment_system_pan_validator.py
panvalidator-0.0.1.dist-info/LICENSE
panvalidator-0.0.1.dist-info/METADATA
panvalidator-0.0.1.dist-info/WHEEL
panvalidator-0.0.1.dist-info/top_level.txt
panvalidator-0.0.1.dist-info/RECORD
