Metadata-Version: 2.1
Name: panvalidator
Version: 0.0.1
Summary: Primary Account Number validation tool
Home-page: https://github.com/geaden/panvalidator
Author: Gennady Denisov
Author-email: denisovgena@gmail.com
License: Apache
Platform: UNKNOWN
Requires-Python: >=3.6
Requires-Dist: luhn
